flip/project_41/project_41.srcs/sources_1/new/pipe_mips32.v
`timescale 1ns / 1ps
//////////////////////////////////////////////////////////////////////////////////
// Company: 
// Engineer: 
// 
// Create Date: 13.06.2023 12:44:10
// Design Name: 
// Module Name: pipe_mips32
// Project Name: 
// Target Devices: 
// Tool Versions: 
// Description: 
// 
// Dependencies: 
// 
// Revision:
// Revision 0.01 - File Created
// Additional Comments:
// 
//////////////////////////////////////////////////////////////////////////////////


module pipe_mips32(clk1,clk2,MEM_WB_ALUOUT,MEM_WB_IR,EX_MEM_ALUOUT);
input clk1,clk2;
reg [31:0] PC;
reg [31:0]IF_ID_IR,IF_ID_NPC;
 reg [31:0]ID_EX_IR,ID_EX_A,ID_EX_B,ID_EX_IMM;
 reg [31:0]EX_MEM_IR,MEM_WB_LMD;
output reg [31:0]MEM_WB_ALUOUT,MEM_WB_IR,EX_MEM_ALUOUT;
 reg [2:0]ID_EX_TYPE,EX_MEM_TYPE,MEM_WB_TYPE;
reg EX_MEM_cond;
reg[31:0]ID_EX_NPC,EX_MEM_B;
reg [31:0]Reg[0:31];
reg [31:0]Mem[0:1023];
parameter ADD=6'b000000,SUB=6'b000001,AND=6'b000010,OR=6'b000011,
            SLT=6'b000100,MUL=6'b000101,HLT=6'b111111,LW=6'b001000,
            SW=6'b001001,ADDI=6'b001010,SUBI=6'b001011,SLTI=6'b001100,
            BNEQZ=6'b001101,BEQZ=6'b001110;
parameter RR_ALU=3'b000,RM_ALU=3'b001,LOAD=3'b010,STORE=3'b011,BRANCH=3'b100,HALT=3'b101;
reg HALTED;
reg TAKEN_BRANCH;

always @(posedge clk1)    //IF stage
if(HALTED==0)
begin
if(((EX_MEM_IR[31:26]==BEQZ)&&(EX_MEM_cond==1))||((EX_MEM_IR[31:26]==BNEQZ)&&(EX_MEM_cond==0)))
begin
IF_ID_IR <=#2 Mem[EX_MEM_ALUOUT];
TAKEN_BRANCH <= #2 1'b1;
IF_ID_NPC <= #2 EX_MEM_ALUOUT +1;
PC<= #2 EX_MEM_ALUOUT +1;
end
else
begin
IF_ID_IR <=#2 Mem[PC];
IF_ID_NPC <=#2 PC+1;
PC <=#2 PC+1;
end
end


always @(posedge clk2)     //ID stage
if(HALTED == 0)
begin
if(IF_ID_IR[25:21]==5'b00000)
ID_EX_A <= 0;
else
ID_EX_A <= #2 Reg[IF_ID_IR[25:21]];

if (IF_ID_IR[20:16] == 5'b00000)
ID_EX_B<=0;
else
ID_EX_B <=#2 Reg[IF_ID_IR[20:16]];
ID_EX_NPC <=#2 IF_ID_NPC;
ID_EX_IR  <= #2 IF_ID_IR;
ID_EX_IMM <= #2 {{16{IF_ID_IR[15]}},{IF_ID_IR[15:0]}};

case(IF_ID_IR[31:26])
ADD,SUB,AND,OR,SLT,MUL: ID_EX_TYPE <=#2 RR_ALU;
ADDI,SUBI,SLTI:         ID_EX_TYPE<=#2 RM_ALU;
LW:                     ID_EX_TYPE<=#2 LOAD;
SW:                     ID_EX_TYPE<=#2 STORE;
BNEQZ,BEQZ:             ID_EX_TYPE<=#2 BRANCH;
HLT:                    ID_EX_TYPE<=#2 HALT;
default:                ID_EX_TYPE<=#2 HALT;
endcase
end


always @(posedge clk1)    //EX stage
if(HALTED == 0)
begin
EX_MEM_TYPE <=#2 ID_EX_TYPE;
EX_MEM_IR <= #2 ID_EX_IR;
TAKEN_BRANCH <=#2 0;

case(ID_EX_TYPE)
RR_ALU:begin
case(ID_EX_IR[31:26])
ADD:EX_MEM_ALUOUT <=#2 ID_EX_A + ID_EX_B;
SUB:EX_MEM_ALUOUT <=#2 ID_EX_A - ID_EX_B;
AND:EX_MEM_ALUOUT <=#2 ID_EX_A & ID_EX_B;
OR:EX_MEM_ALUOUT  <=#2 ID_EX_A | ID_EX_B;
SLT:EX_MEM_ALUOUT <=#2 ID_EX_A < ID_EX_B;
MUL:EX_MEM_ALUOUT <=#2 ID_EX_A * ID_EX_B;
default:EX_MEM_ALUOUT <=#2 32'hxxxxxxxx;
endcase
end

RM_ALU:begin
case(ID_EX_IR[31:26])
ADDI:EX_MEM_ALUOUT<=#2 ID_EX_A + ID_EX_IMM;
SUBI:EX_MEM_ALUOUT<=#2 ID_EX_A - ID_EX_IMM;
SLTI:EX_MEM_ALUOUT<=#2 ID_EX_A < ID_EX_IMM;
default:EX_MEM_ALUOUT<=#2 32'hxxxxxxxx;
endcase
end


LOAD,STORE:
begin
     EX_MEM_ALUOUT <=#2 ID_EX_A + ID_EX_IMM;
     EX_MEM_B <= #2 ID_EX_B;
end
BRANCH:
begin
     EX_MEM_ALUOUT <=#2 ID_EX_NPC + ID_EX_IMM;
     EX_MEM_cond <= #2 (ID_EX_A == 0);
end
endcase
end


always @(posedge clk2)   //MEM stage
if(HALTED == 0)
begin
MEM_WB_TYPE <= #2 EX_MEM_TYPE;
MEM_WB_IR <=#2 EX_MEM_IR;

case(EX_MEM_TYPE)
RR_ALU,RM_ALU:
    MEM_WB_ALUOUT <= #2 EX_MEM_ALUOUT;
LOAD:
MEM_WB_LMD <= #2 Mem[EX_MEM_ALUOUT];
STORE:
if(TAKEN_BRANCH == 0)
Mem[EX_MEM_ALUOUT]<=#2 EX_MEM_B;
endcase
end


always @(posedge clk1)     //WB stage
begin
if(TAKEN_BRANCH==0)
case(MEM_WB_TYPE)
RR_ALU:Reg[MEM_WB_IR[15:11]] <= #2 MEM_WB_ALUOUT;
RM_ALU:Reg[MEM_WB_IR[20:16]] <=#2 MEM_WB_ALUOUT;
LOAD:Reg[MEM_WB_IR[20:16]] <= #2 MEM_WB_LMD;
HALT:HALTED <=#2 1'b1;
endcase
end
endmodule

flip/project_41/project_41.srcs/sim_1/new/pipeline_tb.v
`timescale 1ns / 1ps
//////////////////////////////////////////////////////////////////////////////////
// Company: 
// Engineer: 
// 
// Create Date: 13.06.2023 17:42:22
// Design Name: 
// Module Name: pipeline_tb
// Project Name: 
// Target Devices: 
// Tool Versions: 
// Description: 
// 
// Dependencies: 
// 
// Revision:
// Revision 0.01 - File Created
// Additional Comments:
// 
//////////////////////////////////////////////////////////////////////////////////


module pipeline_tb;
reg clk1,clk2;
wire [31:0]MEM_WB_ALUOUT,MEM_WB_IR,EX_MEM_ALUOUT;
integer k;
pipe_mips32 A1(clk1,clk2,MEM_WB_ALUOUT,MEM_WB_IR,EX_MEM_ALUOUT);
initial
begin
clk1=0;clk2=0;
repeat(20)
begin
#5 clk1=1;
#5 clk1=0;
#5 clk2=1;
#5 clk2=0;
end
end

initial
begin
for(k=0;k<31;k=k+1)
pipe_mips32.Reg[k]=k;
pipe_mips32.Mem[0]=32'h2801000a;
pipe_mips32.Mem[1]=32'h28020014;
pipe_mips32.Mem[2]=32'h28030019;
pipe_mips32.Mem[3]=32'h0ce77800;
pipe_mips32.Mem[4]=32'h0ce77800;
pipe_mips32.Mem[5]=32'h00222000;
pipe_mips32.Mem[6]=32'h0ce77800;
pipe_mips32.Mem[7]=32'h00832800;
pipe_mips32.Mem[8]=32'hfc000000;


pipe_mips32.HALTED=0;
pipe_mips32.PC=0;
pipe_mips32.TAKEN_BRANCH=0;

#280
for(k=0;k<6;k=k+1)
$display("R%1d - %2d",k,pipe_mips32.Reg[k]);
end

initial
begin
$dumpfile("mips.vcd");
$dumpvars(0,pipeline_tb);
#300
$finish;
end
endmodule

flip/project_41/project_41.sim/sim_1/behav/xsim/mips.vcd
$date
   Tue Jun 13 19:35:11 2023
$end
$version
  2020.2
$end
$timescale
  1ps
$end
$scope module pipeline_tb $end
$var reg 1 ! clk1 $end
$var reg 1 " clk2 $end
$var wire 32 # MEM_WB_ALUOUT [31:0] $end
$var wire 32 $ MEM_WB_IR [31:0] $end
$var wire 32 % EX_MEM_ALUOUT [31:0] $end
$var integer 32 & k $end
$scope module A1 $end
$var wire 1 ' clk1 $end
$var wire 1 ( clk2 $end
$var reg 32 ) PC [31:0] $end
$var reg 32 * IF_ID_IR [31:0] $end
$var reg 32 + IF_ID_NPC [31:0] $end
$var reg 32 , ID_EX_IR [31:0] $end
$var reg 32 - ID_EX_A [31:0] $end
$var reg 32 . ID_EX_B [31:0] $end
$var reg 32 / ID_EX_IMM [31:0] $end
$var reg 32 0 EX_MEM_IR [31:0] $end
$var reg 32 1 MEM_WB_LMD [31:0] $end
$var reg 32 2 MEM_WB_ALUOUT [31:0] $end
$var reg 32 3 MEM_WB_IR [31:0] $end
$var reg 32 4 EX_MEM_ALUOUT [31:0] $end
$var reg 3 5 ID_EX_TYPE [2:0] $end
$var reg 3 6 EX_MEM_TYPE [2:0] $end
$var reg 3 7 MEM_WB_TYPE [2:0] $end
$var reg 1 8 EX_MEM_cond $end
$var reg 32 9 ID_EX_NPC [31:0] $end
$var reg 32 : EX_MEM_B [31:0] $end
$var reg 1 ; HALTED $end
$var reg 1 < TAKEN_BRANCH $end
$upscope $end
$upscope $end
$enddefinitions $end
#0
$dumpvars
0!
0"
bx #
bx $
bx %
b11111 &
0'
0(
b0 )
bx *
bx +
bx ,
bx -
bx .
bx /
bx 0
bx 1
bx 2
bx 3
bx 4
bx 5
bx 6
bx 7
x8
bx 9
bx :
0;
0<
$end
#5000
1!
1'
#7000
b1 )
b101000000000010000000000001010 *
b1 +
#10000
0!
0'
#15000
1"
1(
b0 -
#17000
b101000000000010000000000001010 ,
b1 .
b1010 /
b1 5
b1 9
#20000
0"
0(
#25000
1!
1'
#27000
b1010 %
b10 )
b101000000000100000000000010100 *
b10 +
b101000000000010000000000001010 0
b1010 4
b1 6
#30000
0!
0'
#35000
1"
1(
#37000
b1010 #
b101000000000010000000000001010 $
b101000000000100000000000010100 ,
b10 .
b10100 /
b1010 2
b101000000000010000000000001010 3
b1 7
b10 9
#40000
0"
0(
#45000
1!
1'
#47000
b10100 %
b11 )
b101000000000110000000000011001 *
b11 +
b101000000000100000000000010100 0
b10100 4
#50000
0!
0'
#55000
1"
1(
#57000
b10100 #
b101000000000100000000000010100 $
b101000000000110000000000011001 ,
b11 .
b11001 /
b10100 2
b101000000000100000000000010100 3
b11 9
#60000
0"
0(
#65000
1!
1'
#67000
b11001 %
b100 )
b1100111001110111100000000000 *
b100 +
b101000000000110000000000011001 0
b11001 4
#70000
0!
0'
#75000
1"
1(
#77000
b11001 #
b101000000000110000000000011001 $
b1100111001110111100000000000 ,
b111 -
b111 .
b111100000000000 /
b11001 2
b101000000000110000000000011001 3
b0 5
b100 9
#80000
0"
0(
#85000
1!
1'
#87000
b111 %
b101 )
b101 +
b1100111001110111100000000000 0
b111 4
b0 6
#90000
0!
0'
#95000
1"
1(
#97000
b111 #
b1100111001110111100000000000 $
b111 2
b1100111001110111100000000000 3
b0 7
b101 9
#100000
0"
0(
#105000
1!
1'
#107000
b110 )
b1000100010000000000000 *
b110 +
#110000
0!
0'
#115000
1"
1(
#117000
b1000100010000000000000 ,
b1010 -
b10100 .
b10000000000000 /
b110 9
#120000
0"
0(
#125000
1!
1'
#127000
b11110 %
b111 )
b1100111001110111100000000000 *
b111 +
b1000100010000000000000 0
b11110 4
#130000
0!
0'
#135000
1"
1(
#137000
b11110 #
b1000100010000000000000 $
b1100111001110111100000000000 ,
b111 -
b111 .
b111100000000000 /
b11110 2
b1000100010000000000000 3
b111 9
#140000
0"
0(
#145000
1!
1'
#147000
b111 %
b1000 )
b100000110010100000000000 *
b1000 +
b1100111001110111100000000000 0
b111 4
#150000
0!
0'
#155000
1"
1(
#157000
b111 #
b1100111001110111100000000000 $
b100000110010100000000000 ,
b11110 -
b11001 .
b10100000000000 /
b111 2
b1100111001110111100000000000 3
b1000 9
#160000
0"
0(
#165000
1!
1'
#167000
b110111 %
b1001 )
b11111100000000000000000000000000 *
b1001 +
b100000110010100000000000 0
b110111 4
#170000
0!
0'
#175000
1"
1(
b0 -
b0 .
#177000
b110111 #
b100000110010100000000000 $
b11111100000000000000000000000000 ,
b0 /
b110111 2
b100000110010100000000000 3
b101 5
b1001 9
#180000
0"
0(
#185000
1!
1'
#187000
b1010 )
bx *
b1010 +
b11111100000000000000000000000000 0
b101 6
#190000
0!
0'
#195000
1"
1(
#197000
b11111100000000000000000000000000 $
bx ,
bx -
bx .
bx /
b11111100000000000000000000000000 3
b101 7
b1010 9
#200000
0"
0(
#205000
1!
1'
#207000
b1011 )
b1011 +
bx 0
1;
#210000
0!
0'
#215000
1"
1(
#220000
0"
0(
#225000
1!
1'
#230000
0!
0'
#235000
1"
1(
#240000
0"
0(
#245000
1!
1'
#250000
0!
0'
#255000
1"
1(
#260000
0"
0(
#265000
1!
1'
#270000
0!
0'
#275000
1"
1(
#280000
0"
b110 &
0(
